{
  "version": "7512ab85",
  "entry": {
    "module": "/build/entry.client-3AGQMHVF.js",
    "imports": [
      "/build/_shared/chunk-7BXVU2XQ.js"
    ]
  },
  "routes": {
    "root": {
      "id": "root",
      "path": "",
      "module": "/build/root-2JARTSX3.js",
      "hasAction": false,
      "hasLoader": false,
      "hasCatchBoundary": false,
      "hasErrorBoundary": false
    },
    "routes/index": {
      "id": "routes/index",
      "parentId": "root",
      "index": true,
      "module": "/build/routes/index-JXQXOVMF.js",
      "imports": [
        "/build/_shared/chunk-E4WRBWRQ.js"
      ],
      "hasAction": true,
      "hasLoader": true,
      "hasCatchBoundary": false,
      "hasErrorBoundary": false
    },
    "routes/leaderboards": {
      "id": "routes/leaderboards",
      "parentId": "root",
      "path": "leaderboards",
      "module": "/build/routes/leaderboards-2WBFKBJX.js",
      "imports": [
        "/build/_shared/chunk-E4WRBWRQ.js"
      ],
      "hasAction": false,
      "hasLoader": true,
      "hasCatchBoundary": false,
      "hasErrorBoundary": false
    }
  },
  "url": "/build/manifest-7512AB85.js"
}